peslearn/__init__.py
peslearn/constants.py
peslearn/driver.py
peslearn/input_processor.py
peslearn/datagen/__init__.py
peslearn/datagen/configuration_space.py
peslearn/datagen/molecule.py
peslearn/datagen/outputfile.py
peslearn/datagen/template.py
peslearn/lib/__init__.py
peslearn/lib/induced_permutations.py
peslearn/lib/path.py
peslearn/ml/__init__.py
peslearn/ml/data_sampler.py
peslearn/ml/gaussian_process.py
peslearn/ml/kernel_ridge_reg.py
peslearn/ml/model.py
peslearn/ml/neural_network.py
peslearn/ml/preprocessing_helper.py
peslearn/utils/__init__.py
peslearn/utils/geometry_transform_helper.py
peslearn/utils/parsing_helper.py
peslearn/utils/permutation_helper.py
peslearn/utils/printing_helper.py
peslearn/utils/regex.py
peslearn-1.0.0.dist-info/LICENSE
peslearn-1.0.0.dist-info/METADATA
peslearn-1.0.0.dist-info/WHEEL
peslearn-1.0.0.dist-info/top_level.txt
peslearn-1.0.0.dist-info/zip-safe
peslearn-1.0.0.dist-info/RECORD
