Metadata-Version: 2.1
Name: peslearn
Version: 1.0.0
Summary: Automated Construction of Machine Learning Models of Molecular Potential Energy Surfaces.
Home-page: https://github.com/CCQC/PES-Learn
Author: Adam Abbott, Ian Beck
License: BSD-3-Clause
Requires-Python: >=3.8
License-File: LICENSE
Requires-Dist: numpy >=1.7
Requires-Dist: GPy >=1.9
Requires-Dist: scikit-learn >=0.20
Requires-Dist: pandas >=0.24
Requires-Dist: hyperopt >=0.1.1
Requires-Dist: cclib >=1.6
Requires-Dist: torch >=1.0.1
Requires-Dist: joblib >=1.3.0
Requires-Dist: qcelemental >=0.27.1
Requires-Dist: qcengine >=0.26.0
Provides-Extra: docs
Requires-Dist: sphinx ==1.2.3 ; extra == 'docs'
Requires-Dist: sphinxcontrib-napoleon ; extra == 'docs'
Requires-Dist: sphinx-book-theme ; extra == 'docs'
Requires-Dist: sphinx-copybutton ; extra == 'docs'
Requires-Dist: numpydoc ; extra == 'docs'
Provides-Extra: tests
Requires-Dist: pytest-cov ; extra == 'tests'
